aliyunsdkquickbi_public/__init__.py
aliyunsdkquickbi_public/request/__init__.py
aliyunsdkquickbi_public/request/v20220101/AddDataLevelPermissionRuleUsersRequest.py
aliyunsdkquickbi_public/request/v20220101/AddDataLevelPermissionWhiteListRequest.py
aliyunsdkquickbi_public/request/v20220101/AddDataSourceRequest.py
aliyunsdkquickbi_public/request/v20220101/AddShareReportRequest.py
aliyunsdkquickbi_public/request/v20220101/AddUserGroupMemberRequest.py
aliyunsdkquickbi_public/request/v20220101/AddUserGroupMembersRequest.py
aliyunsdkquickbi_public/request/v20220101/AddUserRequest.py
aliyunsdkquickbi_public/request/v20220101/AddUserTagMetaRequest.py
aliyunsdkquickbi_public/request/v20220101/AddUserToWorkspaceRequest.py
aliyunsdkquickbi_public/request/v20220101/AddWorkspaceUsersRequest.py
aliyunsdkquickbi_public/request/v20220101/AllotDatasetAccelerationTaskRequest.py
aliyunsdkquickbi_public/request/v20220101/AuthorizeMenuRequest.py
aliyunsdkquickbi_public/request/v20220101/BatchAddFeishuUsersRequest.py
aliyunsdkquickbi_public/request/v20220101/CancelAuthorizationMenuRequest.py
aliyunsdkquickbi_public/request/v20220101/CancelCollectionRequest.py
aliyunsdkquickbi_public/request/v20220101/CancelReportShareRequest.py
aliyunsdkquickbi_public/request/v20220101/ChangeVisibilityModelRequest.py
aliyunsdkquickbi_public/request/v20220101/CheckDatasetExistedRequest.py
aliyunsdkquickbi_public/request/v20220101/CheckOrganizationMemberRequest.py
aliyunsdkquickbi_public/request/v20220101/CheckReadableRequest.py
aliyunsdkquickbi_public/request/v20220101/CreateCubeBySqlRequest.py
aliyunsdkquickbi_public/request/v20220101/CreateDatasetRequest.py
aliyunsdkquickbi_public/request/v20220101/CreateTicket4CopilotRequest.py
aliyunsdkquickbi_public/request/v20220101/CreateTicketRequest.py
aliyunsdkquickbi_public/request/v20220101/CreateUserGroupRequest.py
aliyunsdkquickbi_public/request/v20220101/CreateWorkspaceRequest.py
aliyunsdkquickbi_public/request/v20220101/DataInterpretationRequest.py
aliyun_python_sdk_quickbi_public-2.1.20.dist-info/LICENSE
aliyun_python_sdk_quickbi_public-2.1.20.dist-info/METADATA
aliyun_python_sdk_quickbi_public-2.1.20.dist-info/WHEEL
aliyun_python_sdk_quickbi_public-2.1.20.dist-info/top_level.txt
aliyun_python_sdk_quickbi_public-2.1.20.dist-info/RECORD
